gpt_json/__init__.py
gpt_json/enums.py
gpt_json/exceptions.py
gpt_json/fn_calling.py
gpt_json/gpt.py
gpt_json/models.py
gpt_json/parsers.py
gpt_json/prompts.py
gpt_json/py.typed
gpt_json/streaming.py
gpt_json/tests/__init__.py
gpt_json/tests/conftest.py
gpt_json/tests/shared.py
gpt_json/tests/test_api.py
gpt_json/tests/test_fixtures.py
gpt_json/tests/test_fn_calling.py
gpt_json/tests/test_gpt.py
gpt_json/tests/test_models.py
gpt_json/tests/test_parsers.py
gpt_json/tests/test_prompts.py
gpt_json/tests/test_streaming.py
gpt_json/tests/test_transformations.py
gpt_json/tests/test_truncation.py
gpt_json/tests/utils/streaming_utils.py
gpt_json/tests/utils/test_streaming_utils.py
gpt_json/transformations.py
gpt_json/truncation.py
gpt_json/types_oai.py
gpt_json-0.5.1.dist-info/LICENSE
gpt_json-0.5.1.dist-info/METADATA
gpt_json-0.5.1.dist-info/WHEEL
gpt_json-0.5.1.dist-info/RECORD
