Metadata-Version: 2.1
Name: gpt-json
Version: 0.5.1
Summary: Structured and typehinted GPT responses in Python.
Author: Pierce Freeman
Author-email: pierce@freeman.vc
Requires-Python: >=3.11,<4.0
Classifier: Programming Language :: Python :: 3
Classifier: Programming Language :: Python :: 3.11
Classifier: Programming Language :: Python :: 3.12
Requires-Dist: backoff (>=2.2.1,<3.0.0)
Requires-Dist: openai (>=1.16.2,<2.0.0)
Requires-Dist: pydantic (>2.0.0,<3.0.0)
Requires-Dist: tiktoken (>=0.3.3,<0.4.0)
